velintegrator/__init__.py
velintegrator/handler.py
velintegrator/sdk.py
velintegrator-1.1.5.dist-info/METADATA
velintegrator-1.1.5.dist-info/WHEEL
velintegrator-1.1.5.dist-info/top_level.txt
velintegrator-1.1.5.dist-info/RECORD
