Metadata-Version: 2.1
Name: velintegrator
Version: 1.1.5
Summary: Veli Third Party Integrator
Author: Dachi
Author-email: dvadachkoria@veli.store
